{
    "全国中小企业股份转让系统监管": {
        "url": "http://www.neeq.com.cn/disclosure/supervise.html",
        "check": true,
        "func": "www_neeq_com_cn"
    },
    "中国仲裁网": {
        "url": "http://www.china-arbitration.com/",
        "check": true,
        "func": "www_china_arbitration_com"
    },
    "国家企业信用信息公示系统": {
        "url": "http://www.gsxt.gov.cn/index.html",
        "check": true,
        "func": "www_gsxt_gov_cn"
    },
    "中国裁判文书网": {
        "url": "https://wenshu.court.gov.cn/",
        "check": true,
        "func": "wenshu_court_gov_cn"
    },
    "国家产品质量信用信息平台": {
        "url": "http://zlxy.ancc.org.cn/",
        "check": true,
        "func": "zlxy_ancc_org_cn"
    },
    "百度": {
        "url": "https://www.baidu.com/",
        "check": true,
        "func": "www_baidu_com"
    }
}
